{"metadata":[],"pages":[{"margins":{"top":-1,"left":-1,"bottom":-1,"right":-1},"box":{"l":0,"t":0,"w":595,"h":842},"rotation":{"degrees":0,"origin":{"x":0,"y":0},"translation":{"x":0,"y":0}},"pageNumber":1,"elements":[{"id":528,"type":"heading","properties":{"order":0},"metadata":[],"box":{"l":70.78,"t":93.53,"w":380.28,"h":24},"content":[{"id":469,"type":"line","properties":{"order":0},"metadata":[],"box":{"l":70.78,"t":93.53,"w":380.28,"h":24},"content":[{"id":5,"type":"word","properties":{"order":0},"metadata":[],"box":{"l":70.78,"t":93.53,"w":61.67,"h":24},"content":"Parsr:","font":1},{"id":6,"type":"word","properties":{"order":1},"metadata":[],"box":{"l":142.72,"t":93.53,"w":41.11,"h":24},"content":"Turn","font":1},{"id":7,"type":"word","properties":{"order":2},"metadata":[],"box":{"l":194.11,"t":93.53,"w":41.11,"h":24},"content":"your","font":1},{"id":8,"type":"word","properties":{"order":3},"metadata":[],"box":{"l":245.5,"t":93.53,"w":92.5,"h":24},"content":"documents","font":1},{"id":9,"type":"word","properties":{"order":4},"metadata":[],"box":{"l":348.28,"t":93.53,"w":41.11,"h":24},"content":"into","font":1},{"id":10,"type":"word","properties":{"order":5},"metadata":[],"box":{"l":399.67,"t":93.53,"w":51.39,"h":24},"content":"data!","font":1}]}],"level":1},{"id":519,"type":"paragraph","properties":{"order":1},"metadata":[],"box":{"l":70.78,"t":144.05,"w":432.55,"h":60},"content":[{"id":470,"type":"line","properties":{"order":1},"metadata":[],"box":{"l":70.78,"t":144.05,"w":417.79,"h":18},"content":[{"id":14,"type":"word","properties":{"order":6},"metadata":[],"box":{"l":70.78,"t":144.05,"w":26.77,"h":18},"content":"Parsr","font":2},{"id":15,"type":"word","properties":{"order":7},"metadata":[],"box":{"l":101.76,"t":151.05,"w":25.79,"h":11},"content":"allows","font":3},{"id":16,"type":"word","properties":{"order":8},"metadata":[],"box":{"l":131.85,"t":151.05,"w":4.3,"h":11},"content":"a","font":3},{"id":17,"type":"word","properties":{"order":9},"metadata":[],"box":{"l":140.44,"t":151.05,"w":17.19,"h":11},"content":"data","font":3},{"id":18,"type":"word","properties":{"order":10},"metadata":[],"box":{"l":161.93,"t":151.05,"w":42.98,"h":11},"content":"scientist,","font":3},{"id":19,"type":"word","properties":{"order":11},"metadata":[],"box":{"l":209.21,"t":151.05,"w":8.6,"h":11},"content":"an","font":3},{"id":20,"type":"word","properties":{"order":12},"metadata":[],"box":{"l":222.1,"t":151.05,"w":34.38,"h":11},"content":"analyst,","font":3},{"id":21,"type":"word","properties":{"order":13},"metadata":[],"box":{"l":260.78,"t":151.05,"w":4.3,"h":11},"content":"a","font":3},{"id":22,"type":"word","properties":{"order":14},"metadata":[],"box":{"l":269.38,"t":151.05,"w":42.98,"h":11},"content":"developer,","font":3},{"id":23,"type":"word","properties":{"order":15},"metadata":[],"box":{"l":316.65,"t":151.05,"w":8.6,"h":11},"content":"or","font":3},{"id":24,"type":"word","properties":{"order":16},"metadata":[],"box":{"l":329.55,"t":151.05,"w":8.6,"h":11},"content":"an","font":3},{"id":25,"type":"word","properties":{"order":17},"metadata":[],"box":{"l":342.44,"t":151.05,"w":42.98,"h":11},"content":"enthusiast","font":3},{"id":26,"type":"word","properties":{"order":18},"metadata":[],"box":{"l":389.72,"t":151.05,"w":8.6,"h":11},"content":"to","font":3},{"id":27,"type":"word","properties":{"order":19},"metadata":[],"box":{"l":402.61,"t":151.05,"w":55.87,"h":11},"content":"automatically","font":3},{"id":28,"type":"word","properties":{"order":20},"metadata":[],"box":{"l":462.78,"t":151.05,"w":25.79,"h":11},"content":"obtain","font":3}]},{"id":471,"type":"line","properties":{"order":2},"metadata":[],"box":{"l":70.78,"t":166.3,"w":429.5,"h":11},"content":[{"id":30,"type":"word","properties":{"order":21},"metadata":[],"box":{"l":70.78,"t":166.3,"w":45.63,"h":11},"content":"structured","font":3},{"id":31,"type":"word","properties":{"order":22},"metadata":[],"box":{"l":120.97,"t":166.3,"w":18.25,"h":11},"content":"data","font":3},{"id":32,"type":"word","properties":{"order":23},"metadata":[],"box":{"l":143.78,"t":166.3,"w":18.25,"h":11},"content":"from","font":3},{"id":33,"type":"word","properties":{"order":24},"metadata":[],"box":{"l":166.6,"t":166.3,"w":4.56,"h":11},"content":"a","font":3},{"id":34,"type":"word","properties":{"order":25},"metadata":[],"box":{"l":175.72,"t":166.3,"w":36.5,"h":11},"content":"compiled","font":3},{"id":35,"type":"word","properties":{"order":26},"metadata":[],"box":{"l":216.79,"t":166.3,"w":13.69,"h":11},"content":"PDF","font":3},{"id":36,"type":"word","properties":{"order":27},"metadata":[],"box":{"l":235.04,"t":166.3,"w":9.13,"h":11},"content":"or","font":3},{"id":37,"type":"word","properties":{"order":28},"metadata":[],"box":{"l":248.73,"t":166.3,"w":9.13,"h":11},"content":"an","font":3},{"id":38,"type":"word","properties":{"order":29},"metadata":[],"box":{"l":262.42,"t":166.3,"w":22.82,"h":11},"content":"image","font":3},{"id":39,"type":"word","properties":{"order":30},"metadata":[],"box":{"l":289.8,"t":166.3,"w":9.13,"h":11},"content":"or","font":3},{"id":40,"type":"word","properties":{"order":31},"metadata":[],"box":{"l":303.49,"t":166.3,"w":31.94,"h":11},"content":"scanned","font":3},{"id":41,"type":"word","properties":{"order":32},"metadata":[],"box":{"l":339.99,"t":166.3,"w":41.07,"h":11},"content":"document.","font":3},{"id":42,"type":"word","properties":{"order":33},"metadata":[],"box":{"l":385.62,"t":166.3,"w":9.13,"h":11},"content":"It","font":3},{"id":43,"type":"word","properties":{"order":34},"metadata":[],"box":{"l":399.31,"t":166.3,"w":9.13,"h":11},"content":"is","font":3},{"id":44,"type":"word","properties":{"order":35},"metadata":[],"box":{"l":413,"t":166.3,"w":4.56,"h":11},"content":"a","font":3},{"id":46,"type":"word","properties":{"order":36},"metadata":[],"box":{"l":422.42,"t":166.3,"w":77.85,"h":11},"content":"minimal-footprint","font":3}]},{"id":472,"type":"line","properties":{"order":3},"metadata":[],"box":{"l":70.78,"t":179.55,"w":432.55,"h":11},"content":[{"id":48,"type":"word","properties":{"order":37},"metadata":[],"box":{"l":70.78,"t":179.55,"w":36.05,"h":11},"content":"document","font":3},{"id":49,"type":"word","properties":{"order":38},"metadata":[],"box":{"l":111.33,"t":179.55,"w":40.55,"h":11},"content":"cleaning,","font":3},{"id":50,"type":"word","properties":{"order":39},"metadata":[],"box":{"l":156.38,"t":179.55,"w":31.54,"h":11},"content":"parsing","font":3},{"id":51,"type":"word","properties":{"order":40},"metadata":[],"box":{"l":192.43,"t":179.55,"w":13.52,"h":11},"content":"and","font":3},{"id":52,"type":"word","properties":{"order":41},"metadata":[],"box":{"l":210.45,"t":179.55,"w":45.06,"h":11},"content":"extraction","font":3},{"id":53,"type":"word","properties":{"order":42},"metadata":[],"box":{"l":260.01,"t":179.55,"w":40.55,"h":11},"content":"toolchain","font":3},{"id":54,"type":"word","properties":{"order":43},"metadata":[],"box":{"l":305.07,"t":179.55,"w":22.53,"h":11},"content":"which","font":3},{"id":55,"type":"word","properties":{"order":44},"metadata":[],"box":{"l":332.11,"t":179.55,"w":40.55,"h":11},"content":"generates","font":3},{"id":56,"type":"word","properties":{"order":45},"metadata":[],"box":{"l":377.16,"t":179.55,"w":31.54,"h":11},"content":"readily","font":3},{"id":57,"type":"word","properties":{"order":46},"metadata":[],"box":{"l":413.21,"t":179.55,"w":45.06,"h":11},"content":"available,","font":3},{"id":58,"type":"word","properties":{"order":47},"metadata":[],"box":{"l":462.77,"t":179.55,"w":40.55,"h":11},"content":"organized","font":3}]},{"id":473,"type":"line","properties":{"order":4},"metadata":[],"box":{"l":70.78,"t":193.05,"w":226.2,"h":11},"content":[{"id":60,"type":"word","properties":{"order":48},"metadata":[],"box":{"l":70.78,"t":193.05,"w":13.31,"h":11},"content":"and","font":3},{"id":61,"type":"word","properties":{"order":49},"metadata":[],"box":{"l":88.52,"t":193.05,"w":26.61,"h":11},"content":"usable","font":3},{"id":62,"type":"word","properties":{"order":50},"metadata":[],"box":{"l":119.56,"t":193.05,"w":17.74,"h":11},"content":"data","font":3},{"id":63,"type":"word","properties":{"order":51},"metadata":[],"box":{"l":141.74,"t":193.05,"w":13.31,"h":11},"content":"for","font":3},{"id":64,"type":"word","properties":{"order":52},"metadata":[],"box":{"l":159.48,"t":193.05,"w":17.74,"h":11},"content":"data","font":3},{"id":65,"type":"word","properties":{"order":53},"metadata":[],"box":{"l":181.66,"t":193.05,"w":44.35,"h":11},"content":"scientists","font":3},{"id":66,"type":"word","properties":{"order":54},"metadata":[],"box":{"l":230.45,"t":193.05,"w":13.31,"h":11},"content":"and","font":3},{"id":67,"type":"word","properties":{"order":55},"metadata":[],"box":{"l":248.19,"t":193.05,"w":48.79,"h":11},"content":"developers.","font":3}]}]},{"id":527,"type":"paragraph","properties":{"order":5},"metadata":[],"box":{"l":70.78,"t":220.08,"w":288.58,"h":11},"content":[{"id":474,"type":"line","properties":{"order":5},"metadata":[],"box":{"l":70.78,"t":220.08,"w":288.58,"h":11},"content":[{"id":71,"type":"word","properties":{"order":56},"metadata":[],"box":{"l":70.78,"t":220.08,"w":42.44,"h":11},"content":"Currently,","font":3},{"id":72,"type":"word","properties":{"order":57},"metadata":[],"box":{"l":117.46,"t":220.08,"w":21.22,"h":11},"content":"Parsr","font":3},{"id":73,"type":"word","properties":{"order":58},"metadata":[],"box":{"l":142.92,"t":220.08,"w":12.73,"h":11},"content":"has","font":3},{"id":74,"type":"word","properties":{"order":59},"metadata":[],"box":{"l":159.9,"t":220.08,"w":16.98,"h":11},"content":"(but","font":3},{"id":75,"type":"word","properties":{"order":60},"metadata":[],"box":{"l":181.12,"t":220.08,"w":8.49,"h":11},"content":"is","font":3},{"id":76,"type":"word","properties":{"order":61},"metadata":[],"box":{"l":193.85,"t":220.08,"w":12.73,"h":11},"content":"not","font":3},{"id":77,"type":"word","properties":{"order":62},"metadata":[],"box":{"l":210.82,"t":220.08,"w":29.71,"h":11},"content":"limited","font":3},{"id":78,"type":"word","properties":{"order":63},"metadata":[],"box":{"l":244.77,"t":220.08,"w":12.73,"h":11},"content":"to)","font":3},{"id":79,"type":"word","properties":{"order":64},"metadata":[],"box":{"l":261.75,"t":220.08,"w":12.73,"h":11},"content":"the","font":3},{"id":80,"type":"word","properties":{"order":65},"metadata":[],"box":{"l":278.73,"t":220.08,"w":38.2,"h":11},"content":"following","font":3},{"id":81,"type":"word","properties":{"order":66},"metadata":[],"box":{"l":321.16,"t":220.08,"w":38.2,"h":11},"content":"features:","font":3}]}]},{"id":520,"type":"paragraph","properties":{"order":6},"metadata":[],"box":{"l":0,"t":0,"w":0,"h":0},"content":[]},{"id":539,"type":"list","properties":{},"metadata":[],"box":{"l":88.78,"t":246.83,"w":351.69,"h":131.77},"isOrdered":true,"firstItemNumber":1,"content":[{"id":529,"type":"paragraph","properties":{},"metadata":[],"box":{"l":88.78,"t":246.83,"w":112.25,"h":11},"content":[{"id":475,"type":"line","properties":{"order":6},"metadata":[],"box":{"l":88.78,"t":246.83,"w":112.25,"h":11},"content":[{"id":87,"type":"word","properties":{"order":68},"metadata":[],"box":{"l":106.8,"t":246.83,"w":18.39,"h":11},"content":"Text","font":3},{"id":88,"type":"word","properties":{"order":69},"metadata":[],"box":{"l":129.78,"t":246.83,"w":22.98,"h":11},"content":"Order","font":3},{"id":89,"type":"word","properties":{"order":70},"metadata":[],"box":{"l":157.36,"t":246.83,"w":43.66,"h":11},"content":"Detection","font":3}]}]},{"id":530,"type":"paragraph","properties":{},"metadata":[],"box":{"l":88.78,"t":260.33,"w":125.24,"h":11},"content":[{"id":476,"type":"line","properties":{"order":7},"metadata":[],"box":{"l":88.78,"t":260.33,"w":125.24,"h":11},"content":[{"id":93,"type":"word","properties":{"order":72},"metadata":[],"box":{"l":106.8,"t":260.33,"w":20.42,"h":11},"content":"Page","font":3},{"id":94,"type":"word","properties":{"order":73},"metadata":[],"box":{"l":132.33,"t":260.33,"w":30.63,"h":11},"content":"Number","font":3},{"id":95,"type":"word","properties":{"order":74},"metadata":[],"box":{"l":168.07,"t":260.33,"w":45.95,"h":11},"content":"Detection","font":3}]}]},{"id":531,"type":"paragraph","properties":{},"metadata":[],"box":{"l":88.78,"t":273.57,"w":130.02,"h":11},"content":[{"id":477,"type":"line","properties":{"order":8},"metadata":[],"box":{"l":88.78,"t":273.57,"w":130.02,"h":11},"content":[{"id":99,"type":"word","properties":{"order":76},"metadata":[],"box":{"l":106.8,"t":273.57,"w":64.46,"h":11},"content":"Header-Footer","font":3},{"id":100,"type":"word","properties":{"order":77},"metadata":[],"box":{"l":176.05,"t":273.57,"w":42.75,"h":11},"content":"Detection","font":3}]}]},{"id":532,"type":"paragraph","properties":{},"metadata":[],"box":{"l":88.78,"t":287.1,"w":178.22,"h":11},"content":[{"id":478,"type":"line","properties":{"order":9},"metadata":[],"box":{"l":88.78,"t":287.1,"w":178.22,"h":11},"content":[{"id":104,"type":"word","properties":{"order":79},"metadata":[],"box":{"l":106.8,"t":287.1,"w":23.56,"h":11},"content":"Table","font":3},{"id":105,"type":"word","properties":{"order":80},"metadata":[],"box":{"l":135.07,"t":287.1,"w":42.4,"h":11},"content":"Detection","font":3},{"id":106,"type":"word","properties":{"order":81},"metadata":[],"box":{"l":182.18,"t":287.1,"w":14.13,"h":11},"content":"and","font":3},{"id":107,"type":"word","properties":{"order":82},"metadata":[],"box":{"l":201.03,"t":287.1,"w":65.96,"h":11},"content":"Reconstruction","font":3}]}]},{"id":533,"type":"paragraph","properties":{},"metadata":[],"box":{"l":88.78,"t":300.6,"w":248.54,"h":11},"content":[{"id":479,"type":"line","properties":{"order":10},"metadata":[],"box":{"l":88.78,"t":300.6,"w":248.54,"h":11},"content":[{"id":111,"type":"word","properties":{"order":84},"metadata":[],"box":{"l":106.8,"t":300.6,"w":28.95,"h":11},"content":"Named","font":3},{"id":113,"type":"word","properties":{"order":85},"metadata":[],"box":{"l":141.55,"t":300.6,"w":26.2,"h":11},"content":"Entity","font":3},{"id":115,"type":"word","properties":{"order":86},"metadata":[],"box":{"l":170.33,"t":300.6,"w":49.64,"h":11},"content":"Recognition","font":3},{"id":116,"type":"word","properties":{"order":87},"metadata":[],"box":{"l":224.49,"t":300.6,"w":31.59,"h":11},"content":"(Dates,","font":3},{"id":117,"type":"word","properties":{"order":88},"metadata":[],"box":{"l":260.59,"t":300.6,"w":54.16,"h":11},"content":"Percentages,","font":3},{"id":118,"type":"word","properties":{"order":89},"metadata":[],"box":{"l":319.26,"t":300.6,"w":18.05,"h":11},"content":"etc)","font":3}]}]},{"id":534,"type":"paragraph","properties":{},"metadata":[],"box":{"l":88.78,"t":314.1,"w":351.69,"h":11},"content":[{"id":480,"type":"line","properties":{"order":11},"metadata":[],"box":{"l":88.78,"t":314.1,"w":351.69,"h":11},"content":[{"id":122,"type":"word","properties":{"order":91},"metadata":[],"box":{"l":106.8,"t":314.1,"w":41.22,"h":11},"content":"Key-Value","font":3},{"id":123,"type":"word","properties":{"order":92},"metadata":[],"box":{"l":152.45,"t":314.1,"w":17.27,"h":11},"content":"Pair","font":3},{"id":125,"type":"word","properties":{"order":93},"metadata":[],"box":{"l":174.08,"t":314.1,"w":39.02,"h":11},"content":"Detection","font":3},{"id":126,"type":"word","properties":{"order":94},"metadata":[],"box":{"l":217.43,"t":314.1,"w":17.34,"h":11},"content":"(for","font":3},{"id":127,"type":"word","properties":{"order":95},"metadata":[],"box":{"l":239.11,"t":314.1,"w":13.01,"h":11},"content":"the","font":3},{"id":128,"type":"word","properties":{"order":96},"metadata":[],"box":{"l":256.45,"t":314.1,"w":43.35,"h":11},"content":"extraction","font":3},{"id":129,"type":"word","properties":{"order":97},"metadata":[],"box":{"l":304.14,"t":314.1,"w":8.67,"h":11},"content":"of","font":3},{"id":130,"type":"word","properties":{"order":98},"metadata":[],"box":{"l":317.14,"t":314.1,"w":34.68,"h":11},"content":"specific","font":3},{"id":131,"type":"word","properties":{"order":99},"metadata":[],"box":{"l":356.16,"t":314.1,"w":43.32,"h":11},"content":"form-based","font":3},{"id":132,"type":"word","properties":{"order":100},"metadata":[],"box":{"l":404.29,"t":314.1,"w":36.18,"h":11},"content":"entries)","font":3}]}]},{"id":535,"type":"paragraph","properties":{},"metadata":[],"box":{"l":88.78,"t":327.35,"w":82.51,"h":11},"content":[{"id":481,"type":"line","properties":{"order":12},"metadata":[],"box":{"l":88.78,"t":327.35,"w":82.51,"h":11},"content":[{"id":136,"type":"word","properties":{"order":102},"metadata":[],"box":{"l":106.8,"t":327.35,"w":18.42,"h":11},"content":"Link","font":3},{"id":137,"type":"word","properties":{"order":103},"metadata":[],"box":{"l":129.83,"t":327.35,"w":41.45,"h":11},"content":"Detection","font":3}]}]},{"id":536,"type":"paragraph","properties":{},"metadata":[],"box":{"l":88.78,"t":340.85,"w":101.26,"h":11},"content":[{"id":482,"type":"line","properties":{"order":13},"metadata":[],"box":{"l":88.78,"t":340.85,"w":101.26,"h":11},"content":[{"id":141,"type":"word","properties":{"order":105},"metadata":[],"box":{"l":106.8,"t":340.85,"w":34.27,"h":11},"content":"Heading","font":3},{"id":142,"type":"word","properties":{"order":106},"metadata":[],"box":{"l":145.97,"t":340.85,"w":44.07,"h":11},"content":"Detection","font":3}]}]},{"id":537,"type":"paragraph","properties":{},"metadata":[],"box":{"l":88.78,"t":354.35,"w":311.48,"h":11},"content":[{"id":483,"type":"line","properties":{"order":14},"metadata":[],"box":{"l":88.78,"t":354.35,"w":311.48,"h":11},"content":[{"id":146,"type":"word","properties":{"order":108},"metadata":[],"box":{"l":106.8,"t":354.35,"w":41.1,"h":11},"content":"Document","font":3},{"id":147,"type":"word","properties":{"order":109},"metadata":[],"box":{"l":152.63,"t":354.35,"w":42.86,"h":11},"content":"Hierarchy","font":3},{"id":148,"type":"word","properties":{"order":110},"metadata":[],"box":{"l":200.25,"t":354.35,"w":57.14,"h":11},"content":"Regeneration","font":3},{"id":149,"type":"word","properties":{"order":111},"metadata":[],"box":{"l":262.16,"t":354.35,"w":33.33,"h":11},"content":"(Words,","font":3},{"id":150,"type":"word","properties":{"order":112},"metadata":[],"box":{"l":300.25,"t":354.35,"w":23.81,"h":11},"content":"Lines","font":3},{"id":151,"type":"word","properties":{"order":113},"metadata":[],"box":{"l":328.82,"t":354.35,"w":14.29,"h":11},"content":"and","font":3},{"id":152,"type":"word","properties":{"order":114},"metadata":[],"box":{"l":347.87,"t":354.35,"w":52.38,"h":11},"content":"Paragraphs)","font":3}]}]},{"id":538,"type":"paragraph","properties":{},"metadata":[],"box":{"l":88.78,"t":367.6,"w":131.11,"h":11},"content":[{"id":484,"type":"line","properties":{"order":15},"metadata":[],"box":{"l":88.78,"t":367.6,"w":131.11,"h":11},"content":[{"id":156,"type":"word","properties":{"order":116},"metadata":[],"box":{"l":106.8,"t":367.6,"w":49.17,"h":11},"content":"Whitespace","font":3},{"id":157,"type":"word","properties":{"order":117},"metadata":[],"box":{"l":160.88,"t":367.6,"w":39.33,"h":11},"content":"Removal,","font":3},{"id":158,"type":"word","properties":{"order":118},"metadata":[],"box":{"l":205.13,"t":367.6,"w":14.75,"h":11},"content":"etc","font":3}]}]}]},{"id":521,"type":"paragraph","properties":{"order":16},"metadata":[],"box":{"l":70.78,"t":394.62,"w":420.67,"h":37.75},"content":[{"id":485,"type":"line","properties":{"order":16},"metadata":[],"box":{"l":70.78,"t":394.62,"w":391.42,"h":11},"content":[{"id":162,"type":"word","properties":{"order":119},"metadata":[],"box":{"l":70.78,"t":394.62,"w":54.62,"h":11},"content":"Furthermore,","font":3},{"id":163,"type":"word","properties":{"order":120},"metadata":[],"box":{"l":129.94,"t":394.62,"w":13.65,"h":11},"content":"the","font":3},{"id":164,"type":"word","properties":{"order":121},"metadata":[],"box":{"l":148.15,"t":394.62,"w":36.41,"h":11},"content":"pipeline","font":3},{"id":165,"type":"word","properties":{"order":122},"metadata":[],"box":{"l":189.11,"t":394.62,"w":9.1,"h":11},"content":"is","font":3},{"id":166,"type":"word","properties":{"order":123},"metadata":[],"box":{"l":202.77,"t":394.62,"w":45.51,"h":11},"content":"extensible","font":3},{"id":167,"type":"word","properties":{"order":124},"metadata":[],"box":{"l":252.83,"t":394.62,"w":13.65,"h":11},"content":"and","font":3},{"id":168,"type":"word","properties":{"order":125},"metadata":[],"box":{"l":271.04,"t":394.62,"w":22.76,"h":11},"content":"one’s","font":3},{"id":169,"type":"word","properties":{"order":126},"metadata":[],"box":{"l":298.35,"t":394.62,"w":13.65,"h":11},"content":"own","font":3},{"id":170,"type":"word","properties":{"order":127},"metadata":[],"box":{"l":316.55,"t":394.62,"w":27.31,"h":11},"content":"module","font":3},{"id":171,"type":"word","properties":{"order":128},"metadata":[],"box":{"l":348.41,"t":394.62,"w":13.65,"h":11},"content":"can","font":3},{"id":172,"type":"word","properties":{"order":129},"metadata":[],"box":{"l":366.62,"t":394.62,"w":9.1,"h":11},"content":"be","font":3},{"id":173,"type":"word","properties":{"order":130},"metadata":[],"box":{"l":380.27,"t":394.62,"w":27.31,"h":11},"content":"easily","font":3},{"id":174,"type":"word","properties":{"order":131},"metadata":[],"box":{"l":412.13,"t":394.62,"w":50.07,"h":11},"content":"introduced.","font":3}]},{"id":486,"type":"line","properties":{"order":17},"metadata":[],"box":{"l":70.78,"t":408.12,"w":420.67,"h":11},"content":[{"id":176,"type":"word","properties":{"order":132},"metadata":[],"box":{"l":70.78,"t":408.12,"w":31,"h":11},"content":"Parsr’s","font":3},{"id":177,"type":"word","properties":{"order":133},"metadata":[],"box":{"l":106.2,"t":408.12,"w":44.28,"h":11},"content":"pipeline’s","font":3},{"id":178,"type":"word","properties":{"order":134},"metadata":[],"box":{"l":154.91,"t":408.12,"w":35.42,"h":11},"content":"backbone","font":3},{"id":179,"type":"word","properties":{"order":135},"metadata":[],"box":{"l":194.76,"t":408.12,"w":8.86,"h":11},"content":"is","font":3},{"id":180,"type":"word","properties":{"order":136},"metadata":[],"box":{"l":208.05,"t":408.12,"w":22.14,"h":11},"content":"based","font":3},{"id":181,"type":"word","properties":{"order":137},"metadata":[],"box":{"l":234.61,"t":408.12,"w":8.86,"h":11},"content":"on","font":3},{"id":182,"type":"word","properties":{"order":138},"metadata":[],"box":{"l":247.9,"t":408.12,"w":48.71,"h":11},"content":"Typescript,","font":3},{"id":183,"type":"word","properties":{"order":139},"metadata":[],"box":{"l":301.03,"t":408.12,"w":13.28,"h":11},"content":"but","font":3},{"id":184,"type":"word","properties":{"order":140},"metadata":[],"box":{"l":318.75,"t":408.12,"w":8.86,"h":11},"content":"it","font":3},{"id":185,"type":"word","properties":{"order":141},"metadata":[],"box":{"l":332.03,"t":408.12,"w":13.28,"h":11},"content":"can","font":3},{"id":186,"type":"word","properties":{"order":142},"metadata":[],"box":{"l":349.74,"t":408.12,"w":26.57,"h":11},"content":"easily","font":3},{"id":187,"type":"word","properties":{"order":143},"metadata":[],"box":{"l":380.74,"t":408.12,"w":8.86,"h":11},"content":"be","font":3},{"id":188,"type":"word","properties":{"order":144},"metadata":[],"box":{"l":394.02,"t":408.12,"w":35.42,"h":11},"content":"extended","font":3},{"id":189,"type":"word","properties":{"order":145},"metadata":[],"box":{"l":433.88,"t":408.12,"w":22.14,"h":11},"content":"using","font":3},{"id":190,"type":"word","properties":{"order":146},"metadata":[],"box":{"l":460.45,"t":408.12,"w":31,"h":11},"content":"modules","font":3}]},{"id":487,"type":"line","properties":{"order":18},"metadata":[],"box":{"l":70.78,"t":421.37,"w":261.93,"h":11},"content":[{"id":192,"type":"word","properties":{"order":147},"metadata":[],"box":{"l":70.78,"t":421.37,"w":33.8,"h":11},"content":"plugging","font":3},{"id":193,"type":"word","properties":{"order":148},"metadata":[],"box":{"l":108.8,"t":421.37,"w":16.9,"h":11},"content":"into","font":3},{"id":194,"type":"word","properties":{"order":149},"metadata":[],"box":{"l":129.92,"t":421.37,"w":21.12,"h":11},"content":"tools","font":3},{"id":195,"type":"word","properties":{"order":150},"metadata":[],"box":{"l":155.27,"t":421.37,"w":21.12,"h":11},"content":"built","font":3},{"id":196,"type":"word","properties":{"order":151},"metadata":[],"box":{"l":180.62,"t":421.37,"w":16.9,"h":11},"content":"from","font":3},{"id":197,"type":"word","properties":{"order":152},"metadata":[],"box":{"l":201.74,"t":421.37,"w":29.57,"h":11},"content":"flavors","font":3},{"id":198,"type":"word","properties":{"order":153},"metadata":[],"box":{"l":235.54,"t":421.37,"w":16.9,"h":11},"content":"like","font":3},{"id":199,"type":"word","properties":{"order":154},"metadata":[],"box":{"l":256.66,"t":421.37,"w":25.35,"h":11},"content":"Python","font":3},{"id":200,"type":"word","properties":{"order":155},"metadata":[],"box":{"l":286.23,"t":421.37,"w":8.45,"h":11},"content":"or","font":3},{"id":201,"type":"word","properties":{"order":156},"metadata":[],"box":{"l":298.91,"t":421.37,"w":33.8,"h":11},"content":"Haskell.","font":3}]}]},{"id":522,"type":"paragraph","properties":{"order":19},"metadata":[],"box":{"l":70.78,"t":448.37,"w":436.09,"h":51.28},"content":[{"id":488,"type":"line","properties":{"order":19},"metadata":[],"box":{"l":70.78,"t":448.37,"w":425.78,"h":11},"content":[{"id":207,"type":"word","properties":{"order":157},"metadata":[],"box":{"l":70.78,"t":448.37,"w":22.23,"h":11},"content":"Parsr","font":3},{"id":208,"type":"word","properties":{"order":158},"metadata":[],"box":{"l":97.45,"t":448.37,"w":35.57,"h":11},"content":"supports","font":3},{"id":209,"type":"word","properties":{"order":159},"metadata":[],"box":{"l":137.47,"t":448.37,"w":4.45,"h":11},"content":"a","font":3},{"id":210,"type":"word","properties":{"order":160},"metadata":[],"box":{"l":146.37,"t":448.37,"w":26.68,"h":11},"content":"choice","font":3},{"id":211,"type":"word","properties":{"order":161},"metadata":[],"box":{"l":177.49,"t":448.37,"w":22.23,"h":11},"content":"among","font":3},{"id":212,"type":"word","properties":{"order":162},"metadata":[],"box":{"l":204.17,"t":448.37,"w":35.57,"h":11},"content":"multiple","font":3},{"id":213,"type":"word","properties":{"order":163},"metadata":[],"box":{"l":244.19,"t":448.37,"w":44.47,"h":11},"content":"extraction","font":3},{"id":214,"type":"word","properties":{"order":164},"metadata":[],"box":{"l":293.11,"t":448.37,"w":31.13,"h":11},"content":"engines","font":3},{"id":215,"type":"word","properties":{"order":165},"metadata":[],"box":{"l":328.68,"t":448.37,"w":13.34,"h":11},"content":"for","font":3},{"id":216,"type":"word","properties":{"order":166},"metadata":[],"box":{"l":346.47,"t":448.37,"w":17.79,"h":11},"content":"each","font":3},{"id":217,"type":"word","properties":{"order":167},"metadata":[],"box":{"l":368.7,"t":448.37,"w":17.79,"h":11},"content":"type","font":3},{"id":218,"type":"word","properties":{"order":168},"metadata":[],"box":{"l":390.93,"t":448.37,"w":8.89,"h":11},"content":"of","font":3},{"id":219,"type":"word","properties":{"order":169},"metadata":[],"box":{"l":404.27,"t":448.37,"w":26.68,"h":11},"content":"input.","font":3},{"id":220,"type":"word","properties":{"order":170},"metadata":[],"box":{"l":435.4,"t":448.37,"w":22.23,"h":11},"content":"Parsr","font":3},{"id":221,"type":"word","properties":{"order":171},"metadata":[],"box":{"l":462.08,"t":448.37,"w":34.47,"h":11},"content":"extracts","font":3}]},{"id":489,"type":"line","properties":{"order":20},"metadata":[],"box":{"l":70.78,"t":461.65,"w":436.09,"h":11},"content":[{"id":223,"type":"word","properties":{"order":172},"metadata":[],"box":{"l":70.78,"t":461.65,"w":30.25,"h":11},"content":"textual","font":3},{"id":224,"type":"word","properties":{"order":173},"metadata":[],"box":{"l":105.34,"t":461.65,"w":17.28,"h":11},"content":"data","font":3},{"id":225,"type":"word","properties":{"order":174},"metadata":[],"box":{"l":126.95,"t":461.65,"w":17.28,"h":11},"content":"from","font":3},{"id":226,"type":"word","properties":{"order":175},"metadata":[],"box":{"l":148.55,"t":461.65,"w":12.96,"h":11},"content":"PDF","font":3},{"id":227,"type":"word","properties":{"order":176},"metadata":[],"box":{"l":165.84,"t":461.65,"w":21.61,"h":11},"content":"files","font":3},{"id":228,"type":"word","properties":{"order":177},"metadata":[],"box":{"l":191.76,"t":461.65,"w":21.61,"h":11},"content":"using","font":3},{"id":230,"type":"word","properties":{"order":178},"metadata":[],"box":{"l":217.85,"t":461.65,"w":40.71,"h":11},"content":"pdftojson","font":3},{"id":232,"type":"word","properties":{"order":179},"metadata":[],"box":{"l":263.1,"t":461.65,"w":13.8,"h":11},"content":"and","font":3},{"id":233,"type":"word","properties":{"order":180},"metadata":[],"box":{"l":281.5,"t":461.65,"w":18.4,"h":11},"content":"from","font":3},{"id":234,"type":"word","properties":{"order":181},"metadata":[],"box":{"l":304.49,"t":461.65,"w":27.6,"h":11},"content":"images","font":3},{"id":235,"type":"word","properties":{"order":182},"metadata":[],"box":{"l":336.69,"t":461.65,"w":23,"h":11},"content":"using","font":3},{"id":236,"type":"word","properties":{"order":183},"metadata":[],"box":{"l":364.29,"t":461.65,"w":13.8,"h":11},"content":"OCR","font":3},{"id":237,"type":"word","properties":{"order":184},"metadata":[],"box":{"l":382.69,"t":461.65,"w":36.8,"h":11},"content":"adapters","font":3},{"id":238,"type":"word","properties":{"order":185},"metadata":[],"box":{"l":424.08,"t":461.65,"w":18.4,"h":11},"content":"such","font":3},{"id":239,"type":"word","properties":{"order":186},"metadata":[],"box":{"l":447.08,"t":461.65,"w":9.2,"h":11},"content":"as","font":3},{"id":240,"type":"word","properties":{"order":187},"metadata":[],"box":{"l":460.88,"t":461.65,"w":45.99,"h":11},"content":"tesseract.","font":3}]},{"id":490,"type":"line","properties":{"order":21},"metadata":[],"box":{"l":70.78,"t":475.15,"w":400.3,"h":11},"content":[{"id":242,"type":"word","properties":{"order":188},"metadata":[],"box":{"l":70.78,"t":475.15,"w":13.49,"h":11},"content":"The","font":3},{"id":243,"type":"word","properties":{"order":189},"metadata":[],"box":{"l":88.77,"t":475.15,"w":17.99,"h":11},"content":"user","font":3},{"id":244,"type":"word","properties":{"order":190},"metadata":[],"box":{"l":111.26,"t":475.15,"w":17.99,"h":11},"content":"even","font":3},{"id":245,"type":"word","properties":{"order":191},"metadata":[],"box":{"l":133.74,"t":475.15,"w":13.49,"h":11},"content":"has","font":3},{"id":246,"type":"word","properties":{"order":192},"metadata":[],"box":{"l":151.74,"t":475.15,"w":13.49,"h":11},"content":"the","font":3},{"id":247,"type":"word","properties":{"order":193},"metadata":[],"box":{"l":169.73,"t":475.15,"w":26.99,"h":11},"content":"choice","font":3},{"id":248,"type":"word","properties":{"order":194},"metadata":[],"box":{"l":201.21,"t":475.15,"w":9,"h":11},"content":"to","font":3},{"id":249,"type":"word","properties":{"order":195},"metadata":[],"box":{"l":214.7,"t":475.15,"w":13.49,"h":11},"content":"use","font":3},{"id":250,"type":"word","properties":{"order":196},"metadata":[],"box":{"l":232.7,"t":475.15,"w":13.49,"h":11},"content":"the","font":3},{"id":251,"type":"word","properties":{"order":197},"metadata":[],"box":{"l":250.69,"t":475.15,"w":49.48,"h":11},"content":"proprietary","font":3},{"id":252,"type":"word","properties":{"order":198},"metadata":[],"box":{"l":304.66,"t":475.15,"w":22.49,"h":11},"content":"ABBYY","font":3},{"id":253,"type":"word","properties":{"order":199},"metadata":[],"box":{"l":331.65,"t":475.15,"w":44.98,"h":11},"content":"FineReader","font":3},{"id":254,"type":"word","properties":{"order":200},"metadata":[],"box":{"l":381.12,"t":475.15,"w":35.98,"h":11},"content":"solution","font":3},{"id":255,"type":"word","properties":{"order":201},"metadata":[],"box":{"l":421.6,"t":475.15,"w":13.49,"h":11},"content":"for","font":3},{"id":256,"type":"word","properties":{"order":202},"metadata":[],"box":{"l":439.59,"t":475.15,"w":22.49,"h":11},"content":"using","font":3},{"id":257,"type":"word","properties":{"order":203},"metadata":[],"box":{"l":466.58,"t":475.15,"w":4.5,"h":11},"content":"a","font":3}]},{"id":491,"type":"line","properties":{"order":22},"metadata":[],"box":{"l":70.78,"t":488.65,"w":355.59,"h":11},"content":[{"id":259,"type":"word","properties":{"order":204},"metadata":[],"box":{"l":70.78,"t":488.65,"w":55.81,"h":11},"content":"professional","font":3},{"id":260,"type":"word","properties":{"order":205},"metadata":[],"box":{"l":131.24,"t":488.65,"w":23.26,"h":11},"content":"grade","font":3},{"id":261,"type":"word","properties":{"order":206},"metadata":[],"box":{"l":159.15,"t":488.65,"w":13.95,"h":11},"content":"OCR","font":3},{"id":262,"type":"word","properties":{"order":207},"metadata":[],"box":{"l":177.75,"t":488.65,"w":9.3,"h":11},"content":"as","font":3},{"id":263,"type":"word","properties":{"order":208},"metadata":[],"box":{"l":191.7,"t":488.65,"w":13.95,"h":11},"content":"the","font":3},{"id":264,"type":"word","properties":{"order":209},"metadata":[],"box":{"l":210.31,"t":488.65,"w":32.56,"h":11},"content":"backend","font":3},{"id":265,"type":"word","properties":{"order":210},"metadata":[],"box":{"l":247.52,"t":488.65,"w":13.95,"h":11},"content":"for","font":3},{"id":266,"type":"word","properties":{"order":211},"metadata":[],"box":{"l":266.12,"t":488.65,"w":36.29,"h":11},"content":"enhanced","font":3},{"id":267,"type":"word","properties":{"order":212},"metadata":[],"box":{"l":306.99,"t":488.65,"w":17.69,"h":11},"content":"text","font":3},{"id":268,"type":"word","properties":{"order":213},"metadata":[],"box":{"l":329.09,"t":488.65,"w":48.63,"h":11},"content":"recognition","font":3},{"id":269,"type":"word","properties":{"order":214},"metadata":[],"box":{"l":382.15,"t":488.65,"w":44.21,"h":11},"content":"precision.","font":3}]}]},{"id":523,"type":"paragraph","properties":{"order":23},"metadata":[],"box":{"l":70.78,"t":515.4,"w":437.92,"h":91.77},"content":[{"id":492,"type":"line","properties":{"order":23},"metadata":[],"box":{"l":70.78,"t":515.4,"w":400.97,"h":11},"content":[{"id":273,"type":"word","properties":{"order":215},"metadata":[],"box":{"l":70.78,"t":515.4,"w":22.05,"h":11},"content":"Parsr","font":3},{"id":274,"type":"word","properties":{"order":216},"metadata":[],"box":{"l":97.23,"t":515.4,"w":35.28,"h":11},"content":"provides","font":3},{"id":275,"type":"word","properties":{"order":217},"metadata":[],"box":{"l":136.92,"t":515.4,"w":22.05,"h":11},"content":"users","font":3},{"id":276,"type":"word","properties":{"order":218},"metadata":[],"box":{"l":163.38,"t":515.4,"w":17.64,"h":11},"content":"with","font":3},{"id":277,"type":"word","properties":{"order":219},"metadata":[],"box":{"l":185.43,"t":515.4,"w":26.46,"h":11},"content":"clean,","font":3},{"id":278,"type":"word","properties":{"order":220},"metadata":[],"box":{"l":216.3,"t":515.4,"w":44.1,"h":11},"content":"structured","font":3},{"id":279,"type":"word","properties":{"order":221},"metadata":[],"box":{"l":264.8,"t":515.4,"w":13.23,"h":11},"content":"and","font":3},{"id":280,"type":"word","properties":{"order":222},"metadata":[],"box":{"l":282.44,"t":515.4,"w":61.77,"h":11},"content":"label-enriched","font":3},{"id":281,"type":"word","properties":{"order":223},"metadata":[],"box":{"l":349.03,"t":515.4,"w":49.99,"h":11},"content":"information","font":3},{"id":282,"type":"word","properties":{"order":224},"metadata":[],"box":{"l":403.57,"t":515.4,"w":18.18,"h":11},"content":"set.","font":3},{"id":283,"type":"word","properties":{"order":225},"metadata":[],"box":{"l":426.29,"t":515.4,"w":13.63,"h":11},"content":"The","font":3},{"id":284,"type":"word","properties":{"order":226},"metadata":[],"box":{"l":444.47,"t":515.4,"w":27.27,"h":11},"content":"output","font":3}]},{"id":493,"type":"line","properties":{"order":24},"metadata":[],"box":{"l":70.78,"t":528.9,"w":418.87,"h":11},"content":[{"id":286,"type":"word","properties":{"order":227},"metadata":[],"box":{"l":70.78,"t":528.9,"w":44.09,"h":11},"content":"(formatted","font":3},{"id":287,"type":"word","properties":{"order":228},"metadata":[],"box":{"l":119.28,"t":528.9,"w":8.82,"h":11},"content":"as","font":3},{"id":288,"type":"word","properties":{"order":229},"metadata":[],"box":{"l":132.5,"t":528.9,"w":4.41,"h":11},"content":"a","font":3},{"id":289,"type":"word","properties":{"order":230},"metadata":[],"box":{"l":141.32,"t":528.9,"w":39.68,"h":11},"content":"friendly,","font":3},{"id":290,"type":"word","properties":{"order":231},"metadata":[],"box":{"l":185.41,"t":528.9,"w":44.09,"h":11},"content":"documented","font":3},{"id":291,"type":"word","properties":{"order":232},"metadata":[],"box":{"l":233.91,"t":528.9,"w":17.64,"h":11},"content":"JSON","font":3},{"id":292,"type":"word","properties":{"order":233},"metadata":[],"box":{"l":255.96,"t":528.9,"w":22.05,"h":11},"content":"file)","font":3},{"id":293,"type":"word","properties":{"order":234},"metadata":[],"box":{"l":282.41,"t":528.9,"w":13.23,"h":11},"content":"can","font":3},{"id":294,"type":"word","properties":{"order":235},"metadata":[],"box":{"l":300.05,"t":528.9,"w":35.27,"h":11},"content":"possibly","font":3},{"id":295,"type":"word","properties":{"order":236},"metadata":[],"box":{"l":339.73,"t":528.9,"w":30.86,"h":11},"content":"contain","font":3},{"id":296,"type":"word","properties":{"order":237},"metadata":[],"box":{"l":375.01,"t":528.9,"w":17.64,"h":11},"content":"data","font":3},{"id":297,"type":"word","properties":{"order":238},"metadata":[],"box":{"l":397.05,"t":528.9,"w":17.64,"h":11},"content":"with","font":3},{"id":298,"type":"word","properties":{"order":239},"metadata":[],"box":{"l":419.1,"t":528.9,"w":17.64,"h":11},"content":"fine","font":3},{"id":299,"type":"word","properties":{"order":240},"metadata":[],"box":{"l":441.15,"t":528.9,"w":48.5,"h":11},"content":"granularity","font":3}]},{"id":494,"type":"line","properties":{"order":25},"metadata":[],"box":{"l":70.78,"t":542.42,"w":437.92,"h":11},"content":[{"id":301,"type":"word","properties":{"order":241},"metadata":[],"box":{"l":70.78,"t":542.42,"w":39.7,"h":11},"content":"(bounding","font":3},{"id":302,"type":"word","properties":{"order":242},"metadata":[],"box":{"l":114.89,"t":542.42,"w":22.06,"h":11},"content":"boxes","font":3},{"id":303,"type":"word","properties":{"order":243},"metadata":[],"box":{"l":141.36,"t":542.42,"w":13.23,"h":11},"content":"for","font":3},{"id":304,"type":"word","properties":{"order":244},"metadata":[],"box":{"l":159,"t":542.42,"w":17.65,"h":11},"content":"each","font":3},{"id":305,"type":"word","properties":{"order":245},"metadata":[],"box":{"l":181.06,"t":542.42,"w":26.47,"h":11},"content":"letter","font":3},{"id":306,"type":"word","properties":{"order":246},"metadata":[],"box":{"l":211.94,"t":542.42,"w":8.82,"h":11},"content":"of","font":3},{"id":308,"type":"word","properties":{"order":247},"metadata":[],"box":{"l":225.35,"t":542.42,"w":17.17,"h":11},"content":"each","font":3},{"id":309,"type":"word","properties":{"order":248},"metadata":[],"box":{"l":246.82,"t":542.42,"w":25.76,"h":11},"content":"word),","font":3},{"id":310,"type":"word","properties":{"order":249},"metadata":[],"box":{"l":276.87,"t":542.42,"w":8.59,"h":11},"content":"to","font":3},{"id":311,"type":"word","properties":{"order":250},"metadata":[],"box":{"l":289.75,"t":542.42,"w":42.93,"h":11},"content":"relatively","font":3},{"id":312,"type":"word","properties":{"order":251},"metadata":[],"box":{"l":336.97,"t":542.42,"w":12.88,"h":11},"content":"low","font":3},{"id":313,"type":"word","properties":{"order":252},"metadata":[],"box":{"l":354.14,"t":542.42,"w":38.64,"h":11},"content":"frequency","font":3},{"id":314,"type":"word","properties":{"order":253},"metadata":[],"box":{"l":397.07,"t":542.42,"w":30.05,"h":11},"content":"details","font":3},{"id":315,"type":"word","properties":{"order":254},"metadata":[],"box":{"l":431.42,"t":542.42,"w":17.17,"h":11},"content":"like","font":3},{"id":316,"type":"word","properties":{"order":255},"metadata":[],"box":{"l":452.89,"t":542.42,"w":12.88,"h":11},"content":"the","font":3},{"id":317,"type":"word","properties":{"order":256},"metadata":[],"box":{"l":470.06,"t":542.42,"w":21.47,"h":11},"content":"sizes","font":3},{"id":318,"type":"word","properties":{"order":257},"metadata":[],"box":{"l":495.82,"t":542.42,"w":12.88,"h":11},"content":"and","font":3}]},{"id":495,"type":"line","properties":{"order":26},"metadata":[],"box":{"l":70.78,"t":555.67,"w":95.62,"h":11},"content":[{"id":320,"type":"word","properties":{"order":258},"metadata":[],"box":{"l":70.78,"t":555.67,"w":31.87,"h":11},"content":"margins","font":3},{"id":321,"type":"word","properties":{"order":259},"metadata":[],"box":{"l":107.2,"t":555.67,"w":9.11,"h":11},"content":"of","font":3},{"id":322,"type":"word","properties":{"order":260},"metadata":[],"box":{"l":120.86,"t":555.67,"w":18.21,"h":11},"content":"each","font":3},{"id":323,"type":"word","properties":{"order":261},"metadata":[],"box":{"l":143.63,"t":555.67,"w":22.77,"h":11},"content":"page.","font":3}]},{"id":496,"type":"line","properties":{"order":27},"metadata":[],"box":{"l":70.78,"t":569.17,"w":427.97,"h":11},"content":[{"id":327,"type":"word","properties":{"order":262},"metadata":[],"box":{"l":70.78,"t":569.17,"w":13.66,"h":11},"content":"The","font":3},{"id":328,"type":"word","properties":{"order":263},"metadata":[],"box":{"l":88.99,"t":569.17,"w":18.21,"h":11},"content":"user","font":3},{"id":329,"type":"word","properties":{"order":264},"metadata":[],"box":{"l":111.75,"t":569.17,"w":13.66,"h":11},"content":"can","font":3},{"id":330,"type":"word","properties":{"order":265},"metadata":[],"box":{"l":129.96,"t":569.17,"w":18.21,"h":11},"content":"also","font":3},{"id":331,"type":"word","properties":{"order":266},"metadata":[],"box":{"l":152.73,"t":569.17,"w":36.42,"h":11},"content":"generate","font":3},{"id":332,"type":"word","properties":{"order":267},"metadata":[],"box":{"l":193.7,"t":569.17,"w":31.87,"h":11},"content":"outputs","font":3},{"id":333,"type":"word","properties":{"order":268},"metadata":[],"box":{"l":230.12,"t":569.17,"w":9.11,"h":11},"content":"in","font":3},{"id":334,"type":"word","properties":{"order":269},"metadata":[],"box":{"l":243.78,"t":569.17,"w":13.66,"h":11},"content":"the","font":3},{"id":335,"type":"word","properties":{"order":270},"metadata":[],"box":{"l":261.99,"t":569.17,"w":31.87,"h":11},"content":"formats","font":3},{"id":336,"type":"word","properties":{"order":271},"metadata":[],"box":{"l":298.42,"t":569.17,"w":9.11,"h":11},"content":"of","font":3},{"id":337,"type":"word","properties":{"order":272},"metadata":[],"box":{"l":312.08,"t":569.17,"w":40.98,"h":11},"content":"Markdown,","font":3},{"id":338,"type":"word","properties":{"order":273},"metadata":[],"box":{"l":357.6,"t":569.17,"w":13.66,"h":11},"content":"Raw","font":3},{"id":339,"type":"word","properties":{"order":274},"metadata":[],"box":{"l":375.82,"t":569.17,"w":22.76,"h":11},"content":"Text,","font":3},{"id":340,"type":"word","properties":{"order":275},"metadata":[],"box":{"l":403.13,"t":569.17,"w":18.21,"h":11},"content":"PDF,","font":3},{"id":341,"type":"word","properties":{"order":276},"metadata":[],"box":{"l":425.9,"t":569.17,"w":13.66,"h":11},"content":"CSV","font":3},{"id":342,"type":"word","properties":{"order":277},"metadata":[],"box":{"l":444.11,"t":569.17,"w":18.21,"h":11},"content":"(for","font":3},{"id":343,"type":"word","properties":{"order":278},"metadata":[],"box":{"l":466.87,"t":569.17,"w":31.87,"h":11},"content":"tabular","font":3}]},{"id":497,"type":"line","properties":{"order":28},"metadata":[],"box":{"l":70.78,"t":582.67,"w":420.12,"h":11},"content":[{"id":345,"type":"word","properties":{"order":279},"metadata":[],"box":{"l":70.78,"t":582.67,"w":27.21,"h":11},"content":"data),","font":3},{"id":346,"type":"word","properties":{"order":280},"metadata":[],"box":{"l":102.52,"t":582.67,"w":13.6,"h":11},"content":"and","font":3},{"id":347,"type":"word","properties":{"order":281},"metadata":[],"box":{"l":120.65,"t":582.67,"w":31.74,"h":11},"content":"others.","font":3},{"id":348,"type":"word","properties":{"order":282},"metadata":[],"box":{"l":156.93,"t":582.67,"w":13.6,"h":11},"content":"New","font":3},{"id":349,"type":"word","properties":{"order":283},"metadata":[],"box":{"l":175.06,"t":582.67,"w":27.21,"h":11},"content":"output","font":3},{"id":350,"type":"word","properties":{"order":284},"metadata":[],"box":{"l":206.8,"t":582.67,"w":31.74,"h":11},"content":"formats","font":3},{"id":351,"type":"word","properties":{"order":285},"metadata":[],"box":{"l":243.08,"t":582.67,"w":13.6,"h":11},"content":"can","font":3},{"id":352,"type":"word","properties":{"order":286},"metadata":[],"box":{"l":261.22,"t":582.67,"w":18.14,"h":11},"content":"also","font":3},{"id":353,"type":"word","properties":{"order":287},"metadata":[],"box":{"l":283.89,"t":582.67,"w":9.07,"h":11},"content":"be","font":3},{"id":354,"type":"word","properties":{"order":288},"metadata":[],"box":{"l":297.49,"t":582.67,"w":27.21,"h":11},"content":"easily","font":3},{"id":355,"type":"word","properties":{"order":289},"metadata":[],"box":{"l":329.23,"t":582.67,"w":40.81,"h":11},"content":"generated","font":3},{"id":356,"type":"word","properties":{"order":290},"metadata":[],"box":{"l":374.57,"t":582.67,"w":22.59,"h":11},"content":"using","font":3},{"id":357,"type":"word","properties":{"order":291},"metadata":[],"box":{"l":401.83,"t":582.67,"w":8.91,"h":11},"content":"an","font":3},{"id":358,"type":"word","properties":{"order":292},"metadata":[],"box":{"l":415.19,"t":582.67,"w":44.54,"h":11},"content":"extensible","font":3},{"id":359,"type":"word","properties":{"order":293},"metadata":[],"box":{"l":464.18,"t":582.67,"w":26.72,"h":11},"content":"output","font":3}]},{"id":498,"type":"line","properties":{"order":29},"metadata":[],"box":{"l":70.78,"t":596.17,"w":165.19,"h":11},"content":[{"id":361,"type":"word","properties":{"order":294},"metadata":[],"box":{"l":70.78,"t":596.17,"w":26.79,"h":11},"content":"module","font":3},{"id":362,"type":"word","properties":{"order":295},"metadata":[],"box":{"l":102.03,"t":596.17,"w":26.79,"h":11},"content":"system","font":3},{"id":363,"type":"word","properties":{"order":296},"metadata":[],"box":{"l":133.28,"t":596.17,"w":13.39,"h":11},"content":"for","font":3},{"id":364,"type":"word","properties":{"order":297},"metadata":[],"box":{"l":151.14,"t":596.17,"w":17.86,"h":11},"content":"easy","font":3},{"id":365,"type":"word","properties":{"order":298},"metadata":[],"box":{"l":173.46,"t":596.17,"w":62.5,"h":11},"content":"extensibility.","font":3}]}]},{"id":524,"type":"paragraph","properties":{"order":30},"metadata":[],"box":{"l":70.78,"t":622.92,"w":441.68,"h":37.78},"content":[{"id":499,"type":"line","properties":{"order":30},"metadata":[],"box":{"l":70.78,"t":622.92,"w":398.54,"h":11},"content":[{"id":369,"type":"word","properties":{"order":299},"metadata":[],"box":{"l":70.78,"t":622.92,"w":13.67,"h":11},"content":"The","font":3},{"id":370,"type":"word","properties":{"order":300},"metadata":[],"box":{"l":89,"t":622.92,"w":22.78,"h":11},"content":"Parsr","font":3},{"id":371,"type":"word","properties":{"order":301},"metadata":[],"box":{"l":116.34,"t":622.92,"w":50.13,"h":11},"content":"toolchain’s","font":3},{"id":372,"type":"word","properties":{"order":302},"metadata":[],"box":{"l":171.03,"t":622.92,"w":49.35,"h":11},"content":"open-source","font":3},{"id":373,"type":"word","properties":{"order":303},"metadata":[],"box":{"l":225.21,"t":622.92,"w":46.26,"h":11},"content":"dependency","font":3},{"id":374,"type":"word","properties":{"order":304},"metadata":[],"box":{"l":276.09,"t":622.92,"w":13.88,"h":11},"content":"set","font":3},{"id":375,"type":"word","properties":{"order":305},"metadata":[],"box":{"l":294.59,"t":622.92,"w":9.25,"h":11},"content":"is","font":3},{"id":376,"type":"word","properties":{"order":306},"metadata":[],"box":{"l":308.47,"t":622.92,"w":37,"h":11},"content":"minimal:","font":3},{"id":377,"type":"word","properties":{"order":307},"metadata":[],"box":{"l":350.1,"t":622.92,"w":37,"h":11},"content":"node.js,","font":3},{"id":378,"type":"word","properties":{"order":308},"metadata":[],"box":{"l":391.73,"t":622.92,"w":23.13,"h":11},"content":"qpdf,","font":3},{"id":379,"type":"word","properties":{"order":309},"metadata":[],"box":{"l":419.48,"t":622.92,"w":49.84,"h":11},"content":"mupdf-tools,","font":3}]},{"id":500,"type":"line","properties":{"order":31},"metadata":[],"box":{"l":70.78,"t":636.45,"w":441.68,"h":11},"content":[{"id":381,"type":"word","properties":{"order":310},"metadata":[],"box":{"l":70.78,"t":636.45,"w":54.33,"h":11},"content":"imagemagick,","font":3},{"id":382,"type":"word","properties":{"order":311},"metadata":[],"box":{"l":129.64,"t":636.45,"w":45.28,"h":11},"content":"tesseract,","font":3},{"id":383,"type":"word","properties":{"order":312},"metadata":[],"box":{"l":179.44,"t":636.45,"w":40.75,"h":11},"content":"pdf2json,","font":3},{"id":385,"type":"word","properties":{"order":313},"metadata":[],"box":{"l":224.85,"t":636.45,"w":28.76,"h":11},"content":"pandoc","font":3},{"id":386,"type":"word","properties":{"order":314},"metadata":[],"box":{"l":258.4,"t":636.45,"w":14.38,"h":11},"content":"and","font":3},{"id":387,"type":"word","properties":{"order":315},"metadata":[],"box":{"l":277.58,"t":636.45,"w":38.35,"h":11},"content":"camelot.","font":3},{"id":388,"type":"word","properties":{"order":316},"metadata":[],"box":{"l":320.72,"t":636.45,"w":9.59,"h":11},"content":"An","font":3},{"id":389,"type":"word","properties":{"order":317},"metadata":[],"box":{"l":335.1,"t":636.45,"w":38.35,"h":11},"content":"optional","font":3},{"id":390,"type":"word","properties":{"order":318},"metadata":[],"box":{"l":378.24,"t":636.45,"w":52.73,"h":11},"content":"proprietary","font":3},{"id":391,"type":"word","properties":{"order":319},"metadata":[],"box":{"l":435.76,"t":636.45,"w":47.93,"h":11},"content":"dependency","font":3},{"id":392,"type":"word","properties":{"order":320},"metadata":[],"box":{"l":488.49,"t":636.45,"w":23.97,"h":11},"content":"ABBYY","font":3}]},{"id":501,"type":"line","properties":{"order":32},"metadata":[],"box":{"l":70.78,"t":649.7,"w":143.96,"h":11},"content":[{"id":394,"type":"word","properties":{"order":321},"metadata":[],"box":{"l":70.78,"t":649.7,"w":44.99,"h":11},"content":"FineReader","font":3},{"id":395,"type":"word","properties":{"order":322},"metadata":[],"box":{"l":120.26,"t":649.7,"w":9,"h":11},"content":"is","font":3},{"id":396,"type":"word","properties":{"order":323},"metadata":[],"box":{"l":133.76,"t":649.7,"w":31.49,"h":11},"content":"equally","font":3},{"id":397,"type":"word","properties":{"order":324},"metadata":[],"box":{"l":169.75,"t":649.7,"w":44.99,"h":11},"content":"supported.","font":3}]}]},{"id":525,"type":"paragraph","properties":{"order":33},"metadata":[],"box":{"l":70.78,"t":676.7,"w":443.26,"h":78.02},"content":[{"id":502,"type":"line","properties":{"order":33},"metadata":[],"box":{"l":70.78,"t":676.7,"w":433.81,"h":11},"content":[{"id":403,"type":"word","properties":{"order":325},"metadata":[],"box":{"l":70.78,"t":676.7,"w":14.75,"h":11},"content":"The","font":3},{"id":404,"type":"word","properties":{"order":326},"metadata":[],"box":{"l":90.44,"t":676.7,"w":54.58,"h":11},"content":"ready-to-use","font":3},{"id":405,"type":"word","properties":{"order":327},"metadata":[],"box":{"l":149.75,"t":676.7,"w":54.59,"h":11},"content":"applications","font":3},{"id":406,"type":"word","properties":{"order":328},"metadata":[],"box":{"l":208.89,"t":676.7,"w":22.75,"h":11},"content":"range","font":3},{"id":407,"type":"word","properties":{"order":329},"metadata":[],"box":{"l":236.18,"t":676.7,"w":18.2,"h":11},"content":"from","font":3},{"id":408,"type":"word","properties":{"order":330},"metadata":[],"box":{"l":258.93,"t":676.7,"w":18.2,"h":11},"content":"data","font":3},{"id":409,"type":"word","properties":{"order":331},"metadata":[],"box":{"l":281.67,"t":676.7,"w":22.75,"h":11},"content":"entry","font":3},{"id":410,"type":"word","properties":{"order":332},"metadata":[],"box":{"l":308.97,"t":676.7,"w":13.65,"h":11},"content":"and","font":3},{"id":411,"type":"word","properties":{"order":333},"metadata":[],"box":{"l":327.17,"t":676.7,"w":36.39,"h":11},"content":"document","font":3},{"id":412,"type":"word","properties":{"order":334},"metadata":[],"box":{"l":368.11,"t":676.7,"w":36.39,"h":11},"content":"analysis","font":3},{"id":413,"type":"word","properties":{"order":335},"metadata":[],"box":{"l":409.05,"t":676.7,"w":50.04,"h":11},"content":"automation,","font":3},{"id":414,"type":"word","properties":{"order":336},"metadata":[],"box":{"l":463.64,"t":676.7,"w":40.94,"h":11},"content":"archival,","font":3}]},{"id":503,"type":"line","properties":{"order":34},"metadata":[],"box":{"l":70.78,"t":690.2,"w":75.75,"h":11},"content":[{"id":416,"type":"word","properties":{"order":337},"metadata":[],"box":{"l":70.78,"t":690.2,"w":14.2,"h":11},"content":"and","font":3},{"id":417,"type":"word","properties":{"order":338},"metadata":[],"box":{"l":89.71,"t":690.2,"w":18.94,"h":11},"content":"many","font":3},{"id":418,"type":"word","properties":{"order":339},"metadata":[],"box":{"l":113.39,"t":690.2,"w":33.14,"h":11},"content":"others.","font":3}]},{"id":504,"type":"line","properties":{"order":35},"metadata":[],"box":{"l":70.78,"t":703.45,"w":176.99,"h":11},"content":[{"id":422,"type":"word","properties":{"order":340},"metadata":[],"box":{"l":70.78,"t":703.45,"w":53.1,"h":11},"content":"Furthermore,","font":3},{"id":423,"type":"word","properties":{"order":341},"metadata":[],"box":{"l":128.3,"t":703.45,"w":8.85,"h":11},"content":"it","font":3},{"id":424,"type":"word","properties":{"order":342},"metadata":[],"box":{"l":141.57,"t":703.45,"w":8.85,"h":11},"content":"is","font":3},{"id":425,"type":"word","properties":{"order":343},"metadata":[],"box":{"l":154.84,"t":703.45,"w":17.7,"h":11},"content":"free","font":3},{"id":426,"type":"word","properties":{"order":344},"metadata":[],"box":{"l":176.97,"t":703.45,"w":13.27,"h":11},"content":"and","font":3},{"id":427,"type":"word","properties":{"order":345},"metadata":[],"box":{"l":194.67,"t":703.45,"w":17.7,"h":11},"content":"open","font":3},{"id":428,"type":"word","properties":{"order":346},"metadata":[],"box":{"l":216.79,"t":703.45,"w":30.97,"h":11},"content":"source!","font":3}]},{"id":505,"type":"line","properties":{"order":36},"metadata":[],"box":{"l":70.78,"t":716.97,"w":441.3,"h":11},"content":[{"id":432,"type":"word","properties":{"order":347},"metadata":[],"box":{"l":70.78,"t":716.97,"w":24.26,"h":11},"content":"Parsr","font":4},{"id":433,"type":"word","properties":{"order":348},"metadata":[],"box":{"l":99.75,"t":716.97,"w":14.18,"h":11},"content":"was","font":4},{"id":434,"type":"word","properties":{"order":349},"metadata":[],"box":{"l":118.66,"t":716.97,"w":23.63,"h":11},"content":"built","font":4},{"id":435,"type":"word","properties":{"order":350},"metadata":[],"box":{"l":147.02,"t":716.97,"w":9.45,"h":11},"content":"by","font":4},{"id":436,"type":"word","properties":{"order":351},"metadata":[],"box":{"l":161.2,"t":716.97,"w":14.18,"h":11},"content":"the","font":4},{"id":437,"type":"word","properties":{"order":352},"metadata":[],"box":{"l":180.11,"t":716.97,"w":42.54,"h":11},"content":"community","font":4},{"id":438,"type":"word","properties":{"order":353},"metadata":[],"box":{"l":227.38,"t":716.97,"w":23.63,"h":11},"content":"using","font":4},{"id":439,"type":"word","properties":{"order":354},"metadata":[],"box":{"l":255.74,"t":716.97,"w":63.42,"h":11},"content":"community-made","font":4},{"id":440,"type":"word","properties":{"order":355},"metadata":[],"box":{"l":323.78,"t":716.97,"w":21.9,"h":11},"content":"tools","font":4},{"id":441,"type":"word","properties":{"order":356},"metadata":[],"box":{"l":350.05,"t":716.97,"w":13.14,"h":11},"content":"for","font":4},{"id":442,"type":"word","properties":{"order":357},"metadata":[],"box":{"l":367.57,"t":716.97,"w":13.14,"h":11},"content":"the","font":4},{"id":443,"type":"word","properties":{"order":358},"metadata":[],"box":{"l":385.08,"t":716.97,"w":39.41,"h":11},"content":"community","font":4},{"id":444,"type":"word","properties":{"order":359},"metadata":[],"box":{"l":428.87,"t":716.97,"w":30.65,"h":11},"content":"itself.","font":4},{"id":445,"type":"word","properties":{"order":360},"metadata":[],"box":{"l":463.91,"t":716.97,"w":21.9,"h":11},"content":"Delve","font":4},{"id":446,"type":"word","properties":{"order":361},"metadata":[],"box":{"l":490.18,"t":716.97,"w":21.9,"h":11},"content":"right","font":4}]},{"id":506,"type":"line","properties":{"order":37},"metadata":[],"box":{"l":70.78,"t":730.47,"w":443.26,"h":11},"content":[{"id":448,"type":"word","properties":{"order":362},"metadata":[],"box":{"l":70.78,"t":730.47,"w":13.17,"h":11},"content":"in;","font":4},{"id":449,"type":"word","properties":{"order":363},"metadata":[],"box":{"l":88.33,"t":730.47,"w":21.94,"h":11},"content":"check","font":4},{"id":450,"type":"word","properties":{"order":364},"metadata":[],"box":{"l":114.66,"t":730.47,"w":8.78,"h":11},"content":"it","font":4},{"id":451,"type":"word","properties":{"order":365},"metadata":[],"box":{"l":127.83,"t":730.47,"w":13.17,"h":11},"content":"out","font":4},{"id":452,"type":"word","properties":{"order":366},"metadata":[],"box":{"l":145.38,"t":730.47,"w":13.17,"h":11},"content":"and","font":4},{"id":453,"type":"word","properties":{"order":367},"metadata":[],"box":{"l":162.94,"t":730.47,"w":17.55,"h":11},"content":"help","font":4},{"id":454,"type":"word","properties":{"order":368},"metadata":[],"box":{"l":184.88,"t":730.47,"w":30.72,"h":11},"content":"improve","font":4},{"id":455,"type":"word","properties":{"order":369},"metadata":[],"box":{"l":219.99,"t":730.47,"w":17.55,"h":11},"content":"this","font":4},{"id":456,"type":"word","properties":{"order":370},"metadata":[],"box":{"l":241.93,"t":730.47,"w":30.72,"h":11},"content":"version","font":4},{"id":457,"type":"word","properties":{"order":371},"metadata":[],"box":{"l":277.04,"t":730.47,"w":13.17,"h":11},"content":"0.1","font":4},{"id":458,"type":"word","properties":{"order":372},"metadata":[],"box":{"l":294.6,"t":730.47,"w":26.33,"h":11},"content":"making","font":4},{"id":459,"type":"word","properties":{"order":373},"metadata":[],"box":{"l":325.32,"t":730.47,"w":21.94,"h":11},"content":"Parsr","font":4},{"id":460,"type":"word","properties":{"order":374},"metadata":[],"box":{"l":351.65,"t":730.47,"w":13.17,"h":11},"content":"the","font":4},{"id":461,"type":"word","properties":{"order":375},"metadata":[],"box":{"l":369.21,"t":730.47,"w":35.11,"h":11},"content":"standard","font":4},{"id":462,"type":"word","properties":{"order":376},"metadata":[],"box":{"l":408.7,"t":730.47,"w":13.17,"h":11},"content":"for","font":4},{"id":463,"type":"word","properties":{"order":377},"metadata":[],"box":{"l":426.26,"t":730.47,"w":17.55,"h":11},"content":"data","font":4},{"id":464,"type":"word","properties":{"order":378},"metadata":[],"box":{"l":448.2,"t":730.47,"w":43.89,"h":11},"content":"extraction","font":4},{"id":465,"type":"word","properties":{"order":379},"metadata":[],"box":{"l":496.48,"t":730.47,"w":17.55,"h":11},"content":"from","font":4}]},{"id":507,"type":"line","properties":{"order":38},"metadata":[],"box":{"l":70.78,"t":743.73,"w":52.81,"h":11},"content":[{"id":467,"type":"word","properties":{"order":380},"metadata":[],"box":{"l":70.78,"t":743.73,"w":52.81,"h":11},"content":"documents!","font":4}]}]},{"id":526,"type":"paragraph","properties":{"order":39},"metadata":[],"box":{"l":281.63,"t":814.25,"w":31.79,"h":10},"content":[{"id":508,"type":"line","properties":{"order":39},"metadata":[],"box":{"l":281.63,"t":814.25,"w":31.79,"h":10},"content":[{"id":3,"type":"word","properties":{"order":381},"metadata":[],"box":{"l":281.63,"t":814.25,"w":31.79,"h":10},"content":"Internal","font":5}]}]}]}],"fonts":[{"id":1,"name":"Calibri-Bold,sans-serif","size":24,"weight":"bold","isItalic":false,"isUnderline":false,"color":"#000000","sizeUnit":"px"},{"id":2,"name":"Calibri-Bold,sans-serif","size":18,"weight":"bold","isItalic":false,"isUnderline":false,"color":"#000000","sizeUnit":"px"},{"id":3,"name":"Calibri,sans-serif","size":11,"weight":"normal","isItalic":false,"isUnderline":false,"color":"#000000","sizeUnit":"px"},{"id":4,"name":"Calibri-Italic,sans-serif","size":11,"weight":"normal","isItalic":true,"isUnderline":false,"color":"#000000","sizeUnit":"px"},{"id":5,"name":"Calibri,sans-serif","size":10,"weight":"normal","isItalic":false,"isUnderline":false,"color":"#000000","sizeUnit":"px"}]}